obj_todict/__init__.py
obj_todict/_converter.py
obj_todict-0.1.0.dist-info/LICENSE
obj_todict-0.1.0.dist-info/METADATA
obj_todict-0.1.0.dist-info/WHEEL
obj_todict-0.1.0.dist-info/RECORD
