Metadata-Version: 2.1
Name: obj-todict
Version: 0.1.0
Summary: It is a simple utility to recursively convert objects to dictionaries
Home-page: https://github.com/neural-blade/obj-todict
License: MIT
Keywords: to_dict,object to dict,recursive,serialization,utility,dictionary
Author: neural-blade
Author-email: carmeloscaccianoce@icloud.com
Requires-Python: >=3.10,<4.0
Classifier: Development Status :: 5 - Production/Stable
Classifier: Intended Audience :: Developers
Classifier: License :: OSI Approved :: MIT License
Classifier: Operating System :: OS Independent
Classifier: Programming Language :: Python :: 3
Classifier: Programming Language :: Python :: 3.10
Classifier: Programming Language :: Python :: 3.11
Classifier: Programming Language :: Python :: 3.12
Classifier: Topic :: Software Development :: Libraries :: Python Modules
Project-URL: Repository, https://github.com/neural-blade/obj-todict
